<?xml version="1.0" encoding="iso-8859-1"?>
<document title="XP::Tasks::GUI applications::Widgets">
  <main>
    <references>
      <ref link="tasks">Common Tasks</ref>
    </references>
    <content>
      <title>Additional widgets</title>
      <editor>$Id$</editor>
      
      <para>
        <caption>Filedialog</caption>
        <text>
          The FileDialog widget provides a nicer, more functional
          and very powerful widget to browse for files.
          <code><![CDATA[  // ...
  $dlg= &new FileDialog();
  if (MB_OK == $dlg->show()) {           // OK pressed
    printf("File selected: %s%s\n", $dlg->getDirectory(), $dlg->getFileName());
  }
  // ... ]]></code>
          Check out these to screenshots to see what this dialog
          window looks like:
          <br/><br/>          
          <image alt="Screenshot #1: Showing home directory" src="gui.gtk.widgets.filedialog_home.png"/>
          <br/>
          <image alt="Screenshot #2: Selected a file" src="gui.gtk.widgets.filedialog_open.png"/>
        </text>
      </para>
      <para>
        <caption>MessageBox</caption>
        <text>
          The MessageBox class provides an easy-to-use interface for showing messages.
          
          <code><![CDATA[  // ...
  MessageBox::display(
    'Cannot load the same test config twice!', 
    'Error', 
    MB_OK | MB_ICONWARNING
  );
  // ... ]]></code>
          The above example produces the following window:
          <br/><br/>          
          <image alt="Screenshot #1" src="gui.gtk.widgets.messagebox_warning.png"/>
        </text>
      </para>
    </content>
  </main>
</document>
